{"dt": "2017-12-16 06:17", "min_followers": 10, "min_stars": 73, "users": [["User", "hemanth", "https://avatars0.githubusercontent.com/u/18315?v=4", [["paws-on-es6", "https://github.com/hemanth/paws-on-es6", "Minimalist examples of ES6 functionalities.", 297, "JavaScript"], ["koa-rest", "https://github.com/hemanth/koa-rest", "REST demo with koa.", 184, "JavaScript"], ["node-nightly", "https://github.com/hemanth/node-nightly", "node-nightly at your finger tips! ", 173, "JavaScript"]]], ["User", "threepointone", "https://avatars2.githubusercontent.com/u/18808?v=4", [["glamor", "https://github.com/threepointone/glamor", "inline css for react et al", 2764, "JavaScript"], ["markdown-in-js", "https://github.com/threepointone/markdown-in-js", "inline markdown for react/jsx", 732, "JavaScript"], ["glam", "https://github.com/threepointone/glam", "crazy good css in your js", 415, "JavaScript"], ["redux-react-local", "https://github.com/threepointone/redux-react-local", "local component state via redux", 323, "JavaScript"], ["rakt", "https://github.com/threepointone/rakt", "fast websites, by default ", 272, "JavaScript"], ["ratpack", "https://github.com/threepointone/ratpack", "ready. set. go!", 189, "JavaScript"], ["react-modules", "https://github.com/threepointone/react-modules", "code splitting as a component", 174, "JavaScript"], ["react-springs", "https://github.com/threepointone/react-springs", "react+rebound", 91, "JavaScript"], ["favre", "https://github.com/threepointone/favre", "jsx -> favicon", 80, "JavaScript"]]], ["User", "arvindr21", "https://avatars2.githubusercontent.com/u/2562992?v=4", [["diskDB", "https://github.com/arvindr21/diskDB", "A Lightweight Disk based JSON Database with a MongoDB like API for Node", 348, "JavaScript"], ["blueimp-file-upload-expressjs", "https://github.com/arvindr21/blueimp-file-upload-expressjs", "A simple express module for integrating jQuery File Upload.", 107, "JavaScript"], ["mydashboard", "https://github.com/arvindr21/mydashboard", "node webkit based dashboard app", 96, "JavaScript"], ["cli-adventure-games", "https://github.com/arvindr21/cli-adventure-games", "Text Based Adventure Games built with Node.js", 85, "JavaScript"]]], ["User", "satya164", "https://avatars2.githubusercontent.com/u/1174278?v=4", [["quik", "https://github.com/satya164/quik", ":rocket: A quick way to prototype and build apps with React and Babel with zero-setup.", 413, "JavaScript"], ["react-navigation-addons", "https://github.com/satya164/react-navigation-addons", "Add-ons for React Navigation", 215, "JavaScript"], ["PocketGear", "https://github.com/satya164/PocketGear", "A clean and simple Pok\u00e9dex app for Pok\u00e9mon GO", 118, "JavaScript"]]], ["User", "chinchang", "https://avatars1.githubusercontent.com/u/379918?v=4", [["cta.js", "https://github.com/chinchang/cta.js", "Animate your 'action-to-effect' paths", 1555, "JavaScript"], ["superplaceholder.js", "https://github.com/chinchang/superplaceholder.js", "\u26a1Super charge your input placeholders", 871, "JavaScript"], ["web-maker", "https://github.com/chinchang/web-maker", "A blazing fast & offline frontend playground", 689, "JavaScript"], ["screenlog.js", "https://github.com/chinchang/screenlog.js", "Bring console.log on the screen", 501, "JavaScript"], ["code-blast-codemirror", "https://github.com/chinchang/code-blast-codemirror", "\u2728Particles blasts while typing in Codemirror", 312, "JavaScript"], ["picssel-art", "https://github.com/chinchang/picssel-art", "An app to create pixel art using only CSS", 107, "JavaScript"], ["simplezoom.js", "https://github.com/chinchang/simplezoom.js", "A tiny JavaScript library to preview images, better way!", 78, "JavaScript"]]], ["User", "siddharthkp", "https://avatars0.githubusercontent.com/u/1863771?v=4", [["bundlesize", "https://github.com/siddharthkp/bundlesize", "Keep your bundle size in check", 2258, "JavaScript"], ["cost-of-modules", "https://github.com/siddharthkp/cost-of-modules", "Find out which of your dependencies are slowing you down \ud83d\udc22", 1972, "JavaScript"], ["auto-install", "https://github.com/siddharthkp/auto-install", "Install dependencies as you code \u26a1\ufe0f", 781, "JavaScript"], ["notella", "https://github.com/siddharthkp/notella", "No fluff notes app", 183, "JavaScript"], ["github-build", "https://github.com/siddharthkp/github-build", "Github builds for CI", 117, "JavaScript"], ["atom-import-cost", "https://github.com/siddharthkp/atom-import-cost", "Check the size of the package you import", 106, "JavaScript"], ["css-constructor", "https://github.com/siddharthkp/css-constructor", "\ud83d\udc84 CSS constructor for React components", 86, "JavaScript"]]], ["User", "thetutlage", "https://avatars1.githubusercontent.com/u/1706381?v=4", [["vue-clip", "https://github.com/thetutlage/vue-clip", "Simple and hackable file uploader for VueJs. Supports Vue >= 2.1", 124, "JavaScript"]]], ["User", "shyamseshadri", "https://avatars0.githubusercontent.com/u/229613?v=4", [["angularjs-book", "https://github.com/shyamseshadri/angularjs-book", "Examples and Code snippets from the AngularJS O'Reilly book", 1697, "JavaScript"], ["angularjs-up-and-running", "https://github.com/shyamseshadri/angularjs-up-and-running", "All the source code for the AngularJS Up & Running Book for O'Reilly", 461, "JavaScript"]]], ["User", "ManrajGrover", "https://avatars3.githubusercontent.com/u/5673050?v=4", [["football-cli", "https://github.com/ManrajGrover/football-cli", "\u26bd Command line interface for Hackers who love football", 139, "JavaScript"], ["organize-cli", "https://github.com/ManrajGrover/organize-cli", "\ud83d\udccb Organize your files, imagine cleaning up your downloads in an instant", 114, "JavaScript"]]], ["User", "labnol", "https://avatars2.githubusercontent.com/u/1344071?v=4", [["unsubscribe-gmail", "https://github.com/labnol/unsubscribe-gmail", "Gmail Unsubscribe is written in Google Apps Script to replace Unroll.me for unsubscribing from bulk email. See https://ctrlq.org for more Google Scripts.", 587, "JavaScript"]]], ["User", "gokulkrishh", "https://avatars1.githubusercontent.com/u/2944237?v=4", [["demo-progressive-web-app", "https://github.com/gokulkrishh/demo-progressive-web-app", "\ud83c\udf89 A demo for progressive web application with features like offline, push notifications, background sync etc,", 449, "JavaScript"], ["React-hacker-news", "https://github.com/gokulkrishh/React-hacker-news", "\ud83d\udd11 Hacker News site using React.js (fully responsive site)", 94, "JavaScript"]]], ["User", "znck", "https://avatars0.githubusercontent.com/u/2596484?v=4", [["vue-keynote", "https://github.com/znck/vue-keynote", "Keynote with Vue.js - Build presentations on the go!", 95, "JavaScript"], ["vue-plugin-simple", "https://github.com/znck/vue-plugin-simple", "A template to create vue plugins and shareable components.", 86, "JavaScript"]]], ["User", "gautamkrishnar", "https://avatars2.githubusercontent.com/u/8397274?v=4", []], ["User", "shijuvar", "https://avatars0.githubusercontent.com/u/1546448?v=4", [["react-aspnet", "https://github.com/shijuvar/react-aspnet", "Demo app with React and ASP.NET Web API", 101, "JavaScript"]]], ["User", "skyronic", "https://avatars2.githubusercontent.com/u/80173?v=4", [["vue-spa", "https://github.com/skyronic/vue-spa", "Vue 2 Single Page Application Example (vuex + vue-router)", 386, "JavaScript"]]], ["User", "paramaggarwal", "https://avatars2.githubusercontent.com/u/543981?v=4", [["rn-paper-interface", "https://github.com/paramaggarwal/rn-paper-interface", "Implementation of Facebook Paper-like interactive UI in React Native.", 299, "JavaScript"]]], ["User", "hkirat", "https://avatars2.githubusercontent.com/u/8079861?v=4", [["notification-logger", "https://github.com/hkirat/notification-logger", "Desktop notification for your console Logs", 993, "JavaScript"]]], ["User", "softvar", "https://avatars0.githubusercontent.com/u/4180800?v=4", [["github-plus", "https://github.com/softvar/github-plus", ":rocket: Chrome extension to display size of each file, download link and copy file contents directly to clipboard", 195, "JavaScript"]]], ["User", "nashvail", "https://avatars2.githubusercontent.com/u/4699425?v=4", [["Quttons", "https://github.com/nashvail/Quttons", "Buttons made of Quantum Paper ", 650, "JavaScript"], ["ReactPathMenu", "https://github.com/nashvail/ReactPathMenu", "Path Fly Out menu recreated using React Motion", 232, "JavaScript"]]], ["User", "rishabhp", "https://avatars3.githubusercontent.com/u/933948?v=4", [["bideo.js", "https://github.com/rishabhp/bideo.js", "Fullscreen HTML5 Background Video for the Web.", 3521, "JavaScript"]]], ["User", "jpuri", "https://avatars0.githubusercontent.com/u/2182307?v=4", [["react-draft-wysiwyg", "https://github.com/jpuri/react-draft-wysiwyg", "A Wysiwyg editor build on top of ReactJS and DraftJS. https://jpuri.github.io/react-draft-wysiwyg", 1802, "JavaScript"], ["draftjs-utils", "https://github.com/jpuri/draftjs-utils", "An collection of useful utility functions for DraftJS.", 91, "JavaScript"], ["draftjs-to-html", "https://github.com/jpuri/draftjs-to-html", "Library for converting Draftjs editor content state to HTML", 84, "JavaScript"]]], ["User", "princejwesley", "https://avatars1.githubusercontent.com/u/1622515?v=4", [["Mancy", "https://github.com/princejwesley/Mancy", " >_ Electron based NodeJS REPL :see_no_evil:", 2413, "JavaScript"], ["minimap", "https://github.com/princejwesley/minimap", "A preview of full webpage or its DOM element with flexible positioning and navigation support", 227, "JavaScript"]]], ["User", "ArunMichaelDsouza", "https://avatars0.githubusercontent.com/u/4924614?v=4", [["ng-youtube-embed", "https://github.com/ArunMichaelDsouza/ng-youtube-embed", "AngularJS module to embed Youtube videos with support for Youtube player parameters and JavaScript API for iframe embeds.  Superlight (less than 5KB) and easy to use! Supports Youtube video URLs and IDs. No 3rd party JS dependencies.", 89, "JavaScript"], ["ng-image-appear", "https://github.com/ArunMichaelDsouza/ng-image-appear", "AngularJS Module to make images appear with transition as they load. ", 79, "JavaScript"]]], ["User", "s-yadav", "https://avatars1.githubusercontent.com/u/3096766?v=4", [["react-number-format", "https://github.com/s-yadav/react-number-format", "React component to format numbers in an input or as a text.", 337, "JavaScript"], ["patternLock", "https://github.com/s-yadav/patternLock", "A light weight plugin to simulate android like pattern lock interface for your hybrid app or website.", 293, "JavaScript"], ["angulargrid", "https://github.com/s-yadav/angulargrid", "Pinterest like responsive masonry grid system for angular", 259, "JavaScript"], ["ScrollMenu", "https://github.com/s-yadav/ScrollMenu", "A new interface to replace your old boring scrollbar", 174, "JavaScript"], ["radialIndicator", "https://github.com/s-yadav/radialIndicator", "A simple and light weight circular indicator / progressbar plugin.", 158, "JavaScript"], ["ImageViewer", "https://github.com/s-yadav/ImageViewer", "A zooming and panning plugin inspired by google photos for your web images.", 149, "JavaScript"], ["contextMenu.js", "https://github.com/s-yadav/contextMenu.js", "contextMenu.js is a plugin to create windows like context menu with keyboard interaction, different type of inputs ,trigger events and much more.", 130, "JavaScript"], ["jsonQ", "https://github.com/s-yadav/jsonQ", "A JavaScript library to make manipulation and extraction of data from a JSON very easy and fast.", 122, "JavaScript"]]], ["User", "kayalshri", "https://avatars0.githubusercontent.com/u/1327336?v=4", [["tableExport.jquery.plugin", "https://github.com/kayalshri/tableExport.jquery.plugin", "\"table2JSON\", \"table2XML\", \"table2PNG\",\"table2CSV\",\"table2Excel\",\"table2Word\",\"table2Powerpoint\",\"table2txt\",\"table2PDF\"", 1045, "JavaScript"]]], ["User", "djadmin", "https://avatars1.githubusercontent.com/u/2422581?v=4", [["medium-cli", "https://github.com/djadmin/medium-cli", "Medium for Hackers - :computer: A CLI for Medium Stories.", 511, "JavaScript"]]], ["User", "siriscac", "https://avatars3.githubusercontent.com/u/3730446?v=4", []], ["User", "mbad0la", "https://avatars2.githubusercontent.com/u/8503331?v=4", [["Architect", "https://github.com/mbad0la/Architect", "Hardware Description and Emulation Library in JavaScript", 188, "JavaScript"]]], ["User", "rakeshpai", "https://avatars1.githubusercontent.com/u/86208?v=4", [["pi-gpio", "https://github.com/rakeshpai/pi-gpio", "A simple node.js-based GPIO helper for the Raspberry Pi", 664, "JavaScript"]]], ["User", "hegdeashwin", "https://avatars3.githubusercontent.com/u/4667864?v=4", [["Backbone", "https://github.com/hegdeashwin/Backbone", "This training kit has been developed to learn the basics of Backbone.JS. ", 90, "JavaScript"]]], ["User", "ApoorvSaxena", "https://avatars3.githubusercontent.com/u/307583?v=4", [["lozad.js", "https://github.com/ApoorvSaxena/lozad.js", "\ud83d\udd25  Highly performant, light ~0.7kb and configurable lazy loader in pure JS with no dependencies for responsive images, iframes and more", 3369, "JavaScript"], ["colordrop", "https://github.com/ApoorvSaxena/colordrop", "Interactive Drag & Drop Coloring with Material Design Color palette", 104, "JavaScript"]]], ["User", "akshayejh", "https://avatars3.githubusercontent.com/u/15852743?v=4", []], ["User", "brijeshb42", "https://avatars0.githubusercontent.com/u/717550?v=4", [["medium-draft", "https://github.com/brijeshb42/medium-draft", "\ud83d\udcdd A medium like Rich Text Editor built on draft-js with a focus on keyboard shortcuts.", 993, "JavaScript"], ["kattappa", "https://github.com/brijeshb42/kattappa", "A block based rich text editor.", 94, "JavaScript"]]], ["User", "AnujaK", "https://avatars2.githubusercontent.com/u/1309080?v=4", []], ["User", "codef0rmer", "https://avatars0.githubusercontent.com/u/167227?v=4", [["angular-dragdrop", "https://github.com/codef0rmer/angular-dragdrop", "Implementing jQueryUI Drag and Drop functionality in AngularJS (with Animation) is easier than ever", 1683, "JavaScript"]]], ["User", "puranjayjain", "https://avatars1.githubusercontent.com/u/5458094?v=4", [["md-date-time-picker", "https://github.com/puranjayjain/md-date-time-picker", "An implementation of Material Design Picker components in vanilla CSS, JS, and HTML", 223, "JavaScript"], ["react-materialui-notifications", "https://github.com/puranjayjain/react-materialui-notifications", "Spec compliant notifications for react and material ui users", 221, "JavaScript"]]], ["User", "manavsehgal", "https://avatars3.githubusercontent.com/u/3954692?v=4", [["reactspeedcoding", "https://github.com/manavsehgal/reactspeedcoding", ":rocket: Learn React with 30 reusable components, 15 chapters, and 3 single page apps. Fast start project with JavaScript ES6. React Hot Loading. React Router. Redux. PostCSS, FlexBox styling. Firebase database. Webpack packaging. Enzyme, Mocha, Chai BDD testing. ESLint and StyleLint. Browsersync.", 626, "JavaScript"]]], ["User", "vigzmv", "https://avatars0.githubusercontent.com/u/14950089?v=4", [["what_the_thing", "https://github.com/vigzmv/what_the_thing", ":camera: Point camera at things to learn how to say them in a different language. Android app built with React Native.", 348, "JavaScript"]]], ["User", "vkbansal", "https://avatars0.githubusercontent.com/u/5930351?v=4", [["react-contextmenu", "https://github.com/vkbansal/react-contextmenu", "Context Menu implemented in React", 411, "JavaScript"]]], ["User", "abhiomkar", "https://avatars3.githubusercontent.com/u/47312?v=4", [["flask-react", "https://github.com/abhiomkar/flask-react", "Boilerplate to create lightweight webapp with Flask & React.js", 139, "JavaScript"]]], ["User", "atulmy", "https://avatars3.githubusercontent.com/u/685786?v=4", [["fullstack-graphql", "https://github.com/atulmy/fullstack-graphql", "Simple Fullstack GraphQL Application. API built with Express + GraphQL + Sequelize (supports MySQL, Postgres, Sqlite and MSSQL). WebApp built with React + Redux to access the API. Written in ES6 using Babel + Webpack.", 584, "JavaScript"]]], ["User", "mithunvp", "https://avatars2.githubusercontent.com/u/10061273?v=4", [["ng2Mvc5Demo", "https://github.com/mithunvp/ng2Mvc5Demo", "Using Angular 4 (previously known as Angular 2) in ASP.NET MVC 5 & Visual Studio 2015", 114, "JavaScript"]]], ["User", "sriraman", "https://avatars1.githubusercontent.com/u/2248359?v=4", []], ["User", "chintanbanugaria", "https://avatars3.githubusercontent.com/u/222917?v=4", [["92five", "https://github.com/chintanbanugaria/92five", "Self hosted project management application", 1076, "JavaScript"]]], ["User", "Siddharth11", "https://avatars3.githubusercontent.com/u/5427715?v=4", [["iTunes-Remote", "https://github.com/Siddharth11/iTunes-Remote", "Remotely control iTunes on Mac without Internet \ud83c\udfb6\ud83d\udcf1", 106, "JavaScript"], ["gradStop.js", "https://github.com/Siddharth11/gradStop.js", "JavaScript micro library to generate gradient color stops \ud83c\udff3\ufe0f\u200d\ud83c\udf08", 91, "JavaScript"]]], ["User", "g13n", "https://avatars3.githubusercontent.com/u/38545?v=4", [["ua.js", "https://github.com/g13n/ua.js", "A very small user-agent (browser) and device detection library.", 89, "JavaScript"]]], ["User", "DronRathore", "https://avatars0.githubusercontent.com/u/1112049?v=4", []], ["User", "phenax", "https://avatars2.githubusercontent.com/u/11407672?v=4", [["plasmajs", "https://github.com/phenax/plasmajs", "An isomorphic nodeJS framework based on react", 124, "JavaScript"]]], ["User", "sonalgoyal", "https://avatars3.githubusercontent.com/u/309387?v=4", [["crux", "https://github.com/sonalgoyal/crux", "Crux is a reporting application for HBase. Crux provides a simple web based graphical interface to access HBase, query data and create reports. Crux is open sourced under Apache Software Foundation License v2.0.  ", 100, "JavaScript"]]], ["User", "ciju", "https://avatars1.githubusercontent.com/u/98113?v=4", []], ["User", "rcdexta", "https://avatars3.githubusercontent.com/u/900028?v=4", [["react-event-timeline", "https://github.com/rcdexta/react-event-timeline", "A responsive event timeline in React.js", 163, "JavaScript"]]], ["User", "sureskumar", "https://avatars3.githubusercontent.com/u/1582440?v=4", [["Looper", "https://github.com/sureskumar/Looper", "Looper is a sketch plugin that helps automate duplication of groups and layers. One can control properties like Rotate, Scale and Opacity while duplicating. This powerful combination enables artists and designers to create interesting geometric and organic patterns.", 327, "JavaScript"]]], ["User", "walkingtree", "https://avatars0.githubusercontent.com/u/3946663?v=4", [["chartsly", "https://github.com/walkingtree/chartsly", "Walking Tree Charts package based on Sencha Ext JS & Touch", 85, "JavaScript"]]], ["User", "paramquery", "https://avatars2.githubusercontent.com/u/3147491?v=4", [["grid", "https://github.com/paramquery/grid", "jQuery grid plugin based on jQueryui widget design", 438, "JavaScript"]]], ["User", "samsono", "https://avatars3.githubusercontent.com/u/861285?v=4", [["Easy-Responsive-Tabs-to-Accordion", "https://github.com/samsono/Easy-Responsive-Tabs-to-Accordion", "Easy responsive tabs - is a lightweight jQuery plugin which optimizes normal horizontal or vertical tabs to accordion on multi devices like: web, tablets, Mobile (IPad & IPhone). This plugin adapts the screen size and changes its action accordingly.", 543, "JavaScript"]]], ["User", "thinker3197", "https://avatars1.githubusercontent.com/u/14997260?v=4", [["progressively", "https://github.com/thinker3197/progressively", "A JavaScript library to load images progressively \ud83c\udf07", 483, "JavaScript"]]], ["User", "dhavaln", "https://avatars0.githubusercontent.com/u/207155?v=4", []], ["User", "pocha", "https://avatars3.githubusercontent.com/u/608777?v=4", [["terminal-codelearn", "https://github.com/pocha/terminal-codelearn", "Super fast multi user pseudo bash Terminal in Node.js & SockJS", 77, "JavaScript"]]], ["User", "srameshr", "https://avatars1.githubusercontent.com/u/8149408?v=4", [["ionic-starter-oauth", "https://github.com/srameshr/ionic-starter-oauth", "Ionic starter template that includes Facebook and Google open auth login through native facebook and google apps.", 88, "JavaScript"]]], ["User", "varunon9", "https://avatars0.githubusercontent.com/u/9805036?v=4", []], ["User", "zhirzh", "https://avatars1.githubusercontent.com/u/8132723?v=4", [["flow-babel-webpack-plugin", "https://github.com/zhirzh/flow-babel-webpack-plugin", "Flow typecheck status in Webpack build reports", 95, "JavaScript"]]], ["User", "cubettech", "https://avatars2.githubusercontent.com/u/2525619?v=4", [["myyna", "https://github.com/cubettech/myyna", "Node.js Pinterest Clone Script \u2013 Myyna build your own pinterest", 198, "JavaScript"], ["sleekjs", "https://github.com/cubettech/sleekjs", "Node js MVC Framework by Cubet Techno Labs", 100, "JavaScript"]]], ["User", "atrniv", "https://avatars2.githubusercontent.com/u/1157654?v=4", []], ["User", "kunal", "https://avatars0.githubusercontent.com/u/24815?v=4", []], ["User", "agnivade", "https://avatars1.githubusercontent.com/u/1774000?v=4", []], ["User", "ansumanshah", "https://avatars0.githubusercontent.com/u/3208863?v=4", [["css-in-js", "https://github.com/ansumanshah/css-in-js", "Autocomplete React Native / JS Styles and converting plain CSS to JS styles", 141, "JavaScript"]]], ["User", "kbrgl", "https://avatars1.githubusercontent.com/u/13417496?v=4", []], ["User", "arjunkomath", "https://avatars0.githubusercontent.com/u/2555067?v=4", [["Feline-for-Product-Hunt", "https://github.com/arjunkomath/Feline-for-Product-Hunt", "A beautiful, unofficial Android app for Product Hunt", 83, "JavaScript"]]], ["User", "ishanjain28", "https://avatars3.githubusercontent.com/u/7921368?v=4", []], ["User", "kushal-likhi", "https://avatars0.githubusercontent.com/u/571089?v=4", [["operator-overloading-js", "https://github.com/kushal-likhi/operator-overloading-js", "Simple Operator overloading library for JS.", 89, "JavaScript"]]], ["User", "ashish-chopra", "https://avatars1.githubusercontent.com/u/1948545?v=4", [["angular-gauge", "https://github.com/ashish-chopra/angular-gauge", "A reusable gauge directive for Angular 1.x apps and dashboards", 76, "JavaScript"]]], ["User", "bugzin", "https://avatars1.githubusercontent.com/u/674794?v=4", [["reD3", "https://github.com/bugzin/reD3", "Reusable D3 Charts/Components", 264, "JavaScript"]]], ["User", "0mkara", "https://avatars2.githubusercontent.com/u/13261372?v=4", [["etheratom", "https://github.com/0mkara/etheratom", "Solidity compilation and Ethereum contract execution interface for hackable atom editor", 120, "JavaScript"]]], ["User", "mukeshsoni", "https://avatars2.githubusercontent.com/u/1042954?v=4", [["react-telephone-input", "https://github.com/mukeshsoni/react-telephone-input", "React component for entering and validating international telephone numbers", 191, "JavaScript"]]], ["User", "deadnight7", "https://avatars3.githubusercontent.com/u/3257861?v=4", []], ["User", "marghoobsuleman", "https://avatars2.githubusercontent.com/u/316221?v=4", [["ms-Dropdown", "https://github.com/marghoobsuleman/ms-Dropdown", "Image dropdown - convert your dropdown to image dropdown ", 306, "JavaScript"]]], ["User", "prrashi", "https://avatars0.githubusercontent.com/u/1190354?v=4", [["rateYo", "https://github.com/prrashi/rateYo", "A simple and flexible star rating plugin", 233, "JavaScript"]]], ["User", "kirankalyan5", "https://avatars1.githubusercontent.com/u/13114538?v=4", [["react-native-segmented-control-tab", "https://github.com/kirankalyan5/react-native-segmented-control-tab", "react-native-segmented-control-tab(for Android/iOS)", 109, "JavaScript"]]], ["User", "thatisuday", "https://avatars1.githubusercontent.com/u/5711821?v=4", [["ng-dropzone", "https://github.com/thatisuday/ng-dropzone", ":paperclip: AngularJS directive for Dropzone, an easy to use drag'n'drop file upload library.", 88, "JavaScript"]]], ["User", "sanchitgn", "https://avatars1.githubusercontent.com/u/6015563?v=4", [["remember", "https://github.com/sanchitgn/remember", "The progressive offline Todo app", 209, "JavaScript"]]], ["User", "hjmodha", "https://avatars0.githubusercontent.com/u/5876975?v=4", []], ["User", "akshaykumar6", "https://avatars0.githubusercontent.com/u/2537701?v=4", [["github-js", "https://github.com/akshaykumar6/github-js", "Javascript Plugin over Github APIs.", 198, "JavaScript"]]], ["User", "anoopelias", "https://avatars1.githubusercontent.com/u/798009?v=4", [["boids", "https://github.com/anoopelias/boids", "A fast JavaScript implementation of the boids algorithm", 115, "JavaScript"]]], ["User", "malikshubham827", "https://avatars2.githubusercontent.com/u/13511528?v=4", [["get-me-through", "https://github.com/malikshubham827/get-me-through", "A Free, Offline, Real-Time, Open-source web-app to assist organisers of any event in allowing only authorised/invited people using Face-Recognition Technology or QR Code.", 121, "JavaScript"]]], ["User", "tittojose", "https://avatars2.githubusercontent.com/u/2040019?v=4", []], ["User", "numetriclabz", "https://avatars0.githubusercontent.com/u/5244035?v=4", []], ["User", "mominsamir", "https://avatars3.githubusercontent.com/u/9468921?v=4", [["smDateTimeRangePicker", "https://github.com/mominsamir/smDateTimeRangePicker", "Angular Material Date Picker, DateTime Picker, Date Range Picker, Date Time range picker", 127, "JavaScript"]]], ["User", "mcollina", "https://avatars0.githubusercontent.com/u/52195?v=4", [["mosca", "https://github.com/mcollina/mosca", "MQTT broker as a module", 2090, "JavaScript"], ["autocannon", "https://github.com/mcollina/autocannon", "fast HTTP/1.1 benchmarking tool written in Node.js", 635, "JavaScript"], ["ascoltatori", "https://github.com/mcollina/ascoltatori", "The pub/sub library for node backed by Redis, MongoDB, AMQP (RabbitMQ), ZeroMQ, MQTT (Mosquitto) or just plain node!", 390, "JavaScript"], ["node-coap", "https://github.com/mcollina/node-coap", "CoAP - Node.js style", 294, "JavaScript"], ["msgpack5", "https://github.com/mcollina/msgpack5", "A msgpack v5 implementation for node.js, with extension points / msgpack.org[Node]", 278, "JavaScript"], ["aedes", "https://github.com/mcollina/aedes", "Barebone MQTT broker that can run on any stream server, the node way", 207, "JavaScript"], ["qest", "https://github.com/mcollina/qest", "The Internet of Things broker that loves devices and web developers.", 136, "JavaScript"], ["steed", "https://github.com/mcollina/steed", "horsepower for your modules", 131, "JavaScript"], ["make-promises-safe", "https://github.com/mcollina/make-promises-safe", "A node.js module to make the use of promises safe", 101, "JavaScript"], ["split2", "https://github.com/mcollina/split2", "Split Streams3 style", 88, "JavaScript"], ["bloomrun", "https://github.com/mcollina/bloomrun", "A js pattern matcher", 83, "JavaScript"]]], ["User", "peachananr", "https://avatars1.githubusercontent.com/u/897308?v=4", [["onepage-scroll", "https://github.com/peachananr/onepage-scroll", "Create an Apple-like one page scroller website (iPhone 5S website) with One Page Scroll plugin", 9231, "JavaScript"], ["loading-bar", "https://github.com/peachananr/loading-bar", "Add a Youtube-like loading bar to all your ajax links", 678, "JavaScript"], ["simple-text-rotator", "https://github.com/peachananr/simple-text-rotator", "Add a super simple rotating text to your website with little to no markup", 673, "JavaScript"], ["purejs-onepage-scroll", "https://github.com/peachananr/purejs-onepage-scroll", "The javascript version of the infamous jQuery One Page Scroll without relying on jQuery.", 638, "JavaScript"], ["label_better", "https://github.com/peachananr/label_better", "Label your form input like a boss with beautiful animation and without taking up space", 523, "JavaScript"], ["flat-shadow", "https://github.com/peachananr/flat-shadow", "A small jQuery plugin that will automatically cast a shadow creating depth for your flat UI elements ", 489, "JavaScript"], ["panorama_viewer", "https://github.com/peachananr/panorama_viewer", "Embed panorama photos on your website with Panorama Viewer", 435, "JavaScript"], ["wheel-menu", "https://github.com/peachananr/wheel-menu", "Add a fully customisable Path-like wheel menu button to your website", 400, "JavaScript"], ["notify-better", "https://github.com/peachananr/notify-better", "An all in one jQuery plugin that let you change your favicon, browser's title and more to reflect new notifications", 371, "JavaScript"], ["interactive_3d", "https://github.com/peachananr/interactive_3d", "Create a 3D interactive object using images and one simple JS call", 327, "JavaScript"], ["autofix_anything", "https://github.com/peachananr/autofix_anything", "Fix position of anything on your website automatically with one js call", 322, "JavaScript"], ["tiltedpage_scroll", "https://github.com/peachananr/tiltedpage_scroll", "Create a beautiful 3D tilted effect on scroll with jQuery Tilted Page Scroll plugin", 245, "JavaScript"], ["interactive_bg", "https://github.com/peachananr/interactive_bg", "Create an interactive moving background/object that reacts to viewer's cursor", 216, "JavaScript"], ["tip_cards", "https://github.com/peachananr/tip_cards", "Create a card layout that let your user flip through it like you see on Google Tips", 215, "JavaScript"], ["shuffle-images", "https://github.com/peachananr/shuffle-images", "The Simplest Way to shuffle through images in a Creative Way", 180, "JavaScript"], ["zepto-onepage-scroll", "https://github.com/peachananr/zepto-onepage-scroll", "Zepto One Page Scroll is the javascript version of the infamous jQuery One Page Scroll.", 177, "JavaScript"], ["adaptive-modal", "https://github.com/peachananr/adaptive-modal", "Create modal windows that can be morphed from anything", 167, "JavaScript"], ["immersive-slider", "https://github.com/peachananr/immersive-slider", "Create an immersive slider that changes the whole container to match the viewing slide", 132, "JavaScript"], ["fancy-scroll", "https://github.com/peachananr/fancy-scroll", "Add Overflow Scroll Effect like on iOS/Android but for your website", 125, "JavaScript"], ["jumpto", "https://github.com/peachananr/jumpto", "A plugin that let you create a smooth jump to sub navigational menu in one JS call", 105, "JavaScript"], ["zoom-scroller", "https://github.com/peachananr/zoom-scroller", "Create a Subtle Zoom Animation on Images while Scrolling", 96, "JavaScript"], ["let_it_snow", "https://github.com/peachananr/let_it_snow", "Create and Control a Festive Snow on Your Website using HTML5 Canvas", 81, "JavaScript"]]], ["User", "FezVrasta", "https://avatars2.githubusercontent.com/u/5382443?v=4", [["popper.js", "https://github.com/FezVrasta/popper.js", "A kickass library to manage your poppers", 7007, "JavaScript"], ["snackbarjs", "https://github.com/FezVrasta/snackbarjs", "Create Material Design snackbars and toasts with ease.", 616, "JavaScript"], ["dropdown.js", "https://github.com/FezVrasta/dropdown.js", "A dropdown plugin that does what you expect. (NEEDS MAINTAINER)", 186, "JavaScript"], ["react-resize-aware", "https://github.com/FezVrasta/react-resize-aware", "\u21f2\ud83d\udc41 A simple React component which allows to listen the resize event of itself when it's resized.", 85, "JavaScript"]]], ["User", "ericdrowell", "https://avatars1.githubusercontent.com/u/1498774?v=4", [["KineticJS", "https://github.com/ericdrowell/KineticJS", "KineticJS is an HTML5 Canvas JavaScript framework that extends the 2d context by enabling canvas interactivity for desktop and mobile applications.", 3675, "JavaScript"], ["MeteorCharts", "https://github.com/ericdrowell/MeteorCharts", null, 98, "JavaScript"]]], ["User", "rhiokim", "https://avatars3.githubusercontent.com/u/145777?v=4", [["haroopress", "https://github.com/rhiokim/haroopress", "A static site generator built with Node.js, \"Haroo\" means \"a day\" Support Markdown presentation, Syntax Highlight, Themes", 160, "JavaScript"]]], ["User", "duaraghav8", "https://avatars1.githubusercontent.com/u/12758282?v=4", [["Solium", "https://github.com/duaraghav8/Solium", "Linter to identify and fix style & security issues in Solidity", 237, "JavaScript"]]], ["User", "rpominov", "https://avatars3.githubusercontent.com/u/825702?v=4", [["static-land", "https://github.com/rpominov/static-land", "Specification for common algebraic structures in JavaScript based on Fantasy Land", 367, "JavaScript"], ["fun-task", "https://github.com/rpominov/fun-task", "Abstraction for managing asynchronous code in JS", 216, "JavaScript"], ["svgo-loader", "https://github.com/rpominov/svgo-loader", "svgo loader for webpack", 104, "JavaScript"], ["react-demo", "https://github.com/rpominov/react-demo", "A React-component for creating demos of other components", 81, "JavaScript"], ["fluce", "https://github.com/rpominov/fluce", "[DEPRECATED] Flux with immutable data and pure action handlers", 76, "JavaScript"]]], ["User", "objectivehtml", "https://avatars3.githubusercontent.com/u/685027?v=4", [["FlipClock", "https://github.com/objectivehtml/FlipClock", null, 2247, "JavaScript"], ["Google-Maps-for-Craft", "https://github.com/objectivehtml/Google-Maps-for-Craft", "The complete geolocation toolkit for Craft CMS.", 95, "JavaScript"]]], ["User", "adamalex", "https://avatars0.githubusercontent.com/u/50389?v=4", [["docker-urlarchiver", "https://github.com/adamalex/docker-urlarchiver", "An example of using Docker to package a Node.js script with all its dependencies, including Node.  The example logic saves a URL response to Amazon S3", 110, "JavaScript"]]], ["User", "johanan", "https://avatars0.githubusercontent.com/u/544654?v=4", [["Where-to-eat", "https://github.com/johanan/Where-to-eat", "A quick application to test out using node.js and redis. The javascript has been linted, tested, and minified.", 96, "JavaScript"]]], ["User", "jcla1", "https://avatars0.githubusercontent.com/u/693212?v=4", []], ["User", "dstroot", "https://avatars1.githubusercontent.com/u/1438457?v=4", [["skeleton", "https://github.com/dstroot/skeleton", "Node Express MongoDB  Bootstrap Passport... all rolled up into juicy goodness", 315, "JavaScript"]]], ["User", "chachaxw", "https://avatars1.githubusercontent.com/u/9986672?v=4", [["vue-element-quick-start", "https://github.com/chachaxw/vue-element-quick-start", "Vue2, Vux2, Vue-router2, Element-ui SPA project quick start kit(\u540e\u53f0\u7ba1\u7406\u7cfb\u7edf\u811a\u624b\u67b6)", 110, "JavaScript"]]], ["User", "iraycd", "https://avatars0.githubusercontent.com/u/1450984?v=4", [["brickwork", "https://github.com/iraycd/brickwork", "BrickWork is a reponsive jQuery plugin to create Dynamic layouts", 82, "JavaScript"]]], ["User", "currencybot", "https://avatars0.githubusercontent.com/u/1113533?v=4", [["open-exchange-rates", "https://github.com/currencybot/open-exchange-rates", "Open Exchange Rates API - free / open source hourly-updated currency data for everybody", 205, "JavaScript"]]]]}